clicom/__init__.py
clicom/cli_app.py
clicom-0.0.3.dist-info/LICENSE
clicom-0.0.3.dist-info/WHEEL
clicom-0.0.3.dist-info/METADATA
clicom-0.0.3.dist-info/RECORD
